eda_utils/__init__.py
eda_utils/stats.py
eda_utils/viz.py
priyansheda-0.1.0.dist-info/METADATA
priyansheda-0.1.0.dist-info/WHEEL
priyansheda-0.1.0.dist-info/top_level.txt
priyansheda-0.1.0.dist-info/RECORD
